llama_index/py.typed
llama_index/vector_stores/metal/__init__.py
llama_index/vector_stores/metal/base.py
llama_index_vector_stores_metal-0.3.0.dist-info/METADATA
llama_index_vector_stores_metal-0.3.0.dist-info/WHEEL
llama_index_vector_stores_metal-0.3.0.dist-info/RECORD
